<?xml version="1.0" encoding="UTF-8"?>

<!-- generated on 2026-02-18T20:44:12.515202+08:00 by Eclipse SUMO GUI 1.25.0
<sumoConfiguration xmlns:xsi="http://www.w3.org/2001/XMLSchema-instance" xsi:noNamespaceSchemaLocation="http://sumo.dlr.de/xsd/sumoConfiguration.xsd">

    <input>
        <net-file value="c:\Users\otaku\Documents\Thesis\apriori_civiq\scenarios/bgc_full/final_map.net.xml"/>
        <route-files value="c:\Users\otaku\Documents\Thesis\apriori_civiq\scenarios/bgc_full/wardrop_routes_low.rou.xml"/>
        <additional-files value="c:\Users\otaku\Documents\Thesis\apriori_civiq\scenarios/bgc_full/osm.poly.xml.gz,c:\Users\otaku\Documents\Thesis\apriori_civiq\scenarios/bgc_full/output.add.xml,c:\Users\otaku\Documents\Thesis\apriori_civiq\scenarios/bgc_full/vtypes.add.xml"/>
    </input>

    <output>
        <summary-output value="c:\Users\otaku\Documents\Thesis\apriori_civiq\scenarios/bgc_full/data\summary_low.xml"/>
        <tripinfo-output value="c:\Users\otaku\Documents\Thesis\apriori_civiq\scenarios/bgc_full/data\tripinfo_low.xml"/>
        <statistic-output value="c:\Users\otaku\Documents\Thesis\apriori_civiq\scenarios/bgc_full/data\stats_low.xml"/>
    </output>

    <time>
        <step-length value="1.0"/>
    </time>

    <processing>
        <ignore-route-errors value="true"/>
        <time-to-teleport value="-1"/>
        <tls.actuated.jam-threshold value="30"/>
    </processing>

    <routing>
        <device.rerouting.adaptation-steps value="18"/>
        <device.rerouting.adaptation-interval value="10"/>
    </routing>

    <report>
        <verbose value="true"/>
        <duration-log.statistics value="true"/>
        <no-step-log value="true"/>
    </report>

    <emissions>
        <device.emissions.probability value="1.0"/>
    </emissions>

    <traci_server>
        <remote-port value="51830"/>
    </traci_server>

    <gui_only>
        <gui-settings-file value="c:\Users\otaku\Documents\Thesis\apriori_civiq\scenarios/bgc_full/osm.view.xml"/>
        <start value="true"/>
    </gui_only>

</sumoConfiguration>
-->

<statistics xmlns:xsi="http://www.w3.org/2001/XMLSchema-instance" xsi:noNamespaceSchemaLocation="http://sumo.dlr.de/xsd/statistic_file.xsd">
    <performance clockBegin="392039.83" clockEnd="392055.05" clockDuration="15.22" traciDuration="1.89" realTimeFactor="236.53" vehicleUpdatesPerSecond="12776.54" personUpdatesPerSecond="0.00" begin="0.00" end="3600.00" duration="3600.00"/>
    <vehicles loaded="900" inserted="900" running="60" waiting="0"/>
    <teleports total="0" jam="0" yield="0" wrongLane="0"/>
    <safety collisions="0" emergencyStops="0" emergencyBraking="0"/>
    <persons loaded="0" running="0" jammed="0"/>
    <personTeleports total="0" abortWait="0" wrongDest="0"/>
    <vehicleTripStatistics count="840" routeLength="2237.08" speed="10.27" duration="220.89" waitingTime="40.88" timeLoss="91.29" departDelay="0.01" departDelayWaiting="-1.00" totalTravelTime="185551.00" totalDepartDelay="10.00"/>
    <pedestrianStatistics number="0" routeLength="0.00" duration="0.00" timeLoss="0.00"/>
    <rideStatistics number="0"/>
    <transportStatistics number="0"/>
</statistics>
